py_link_detective/__init__.py
py_link_detective/__main__.py
py_link_detective/detective.py
py_link_detective-1.0.0.dist-info/METADATA
py_link_detective-1.0.0.dist-info/WHEEL
py_link_detective-1.0.0.dist-info/entry_points.txt
py_link_detective-1.0.0.dist-info/RECORD
