Metadata-Version: 2.1
Name: py-link-detective
Version: 1.0.0
Summary: A simple implementation of a dead link detection tool using python asyncio library
Author: Ahmed Bin Nasser
Author-email: ahmednasser.bin@gmail.com
Requires-Python: >=3.10,<4.0
Classifier: Programming Language :: Python :: 3
Classifier: Programming Language :: Python :: 3.10
Classifier: Programming Language :: Python :: 3.11
Classifier: Programming Language :: Python :: 3.12
Requires-Dist: bs4 (>=0.0.2,<0.0.3)
Requires-Dist: httpx (>=0.27.0,<0.28.0)
